mopidy_async_client/__init__.py
mopidy_async_client/client.py
mopidy_async_client/messages.py
mopidy_async_client/mopidy_api.py
mopidy_async_client-0.6.4.dist-info/LICENSE
mopidy_async_client-0.6.4.dist-info/WHEEL
mopidy_async_client-0.6.4.dist-info/METADATA
mopidy_async_client-0.6.4.dist-info/RECORD
