Metadata-Version: 2.1
Name: mopidy-async-client
Version: 0.6.4
Summary: Async Mopidy Client via JSON/RPC Websocket interface
Home-page: https://github.com/SvineruS/mopidy-async-client
License: UNKNOWN
Keywords: mopidy, mpd, async, asyncio, client, player
Author: svinerus
Author-email: svinerus@gmail.com
Requires-Python: >=3.7
Requires-Dist: websockets
